Metadata-Version: 2.1
Name: tsfresh
Version: 0.21.1
Summary: tsfresh extracts relevant characteristics from time series
Home-page: https://github.com/blue-yonder/tsfresh
Author: Maximilian Christ, Nils Braun, Julius Neuffer, Andreas W. Kempa-Liehr
Author-email: max.christ@me.com
License: MIT
Platform: UNKNOWN
Classifier: Development Status :: 4 - Beta
Classifier: Programming Language :: Python
Classifier: Programming Language :: Python :: 3
Classifier: Programming Language :: Python :: 3.9
Classifier: Programming Language :: Python :: 3.10
Classifier: Programming Language :: Python :: 3.11
Classifier: Programming Language :: Python :: 3.12
Classifier: Programming Language :: Python :: 3 :: Only
Classifier: Operating System :: Unix
Classifier: Operating System :: Microsoft :: Windows
Classifier: Operating System :: MacOS
Classifier: Intended Audience :: Science/Research
Classifier: Topic :: Scientific/Engineering
Classifier: Topic :: Software Development
Requires-Python: >=3.9
Requires-Dist: requests>=2.9.1
Requires-Dist: numpy>=1.15.1
Requires-Dist: pandas>=0.25.0
Requires-Dist: statsmodels>=0.13
Requires-Dist: patsy>=0.4.1
Requires-Dist: pywavelets
Requires-Dist: scikit-learn>=0.22.0
Requires-Dist: tqdm>=4.10.0
Requires-Dist: stumpy>=1.7.2
Requires-Dist: cloudpickle
Requires-Dist: scipy>=1.2.0; python_version < "3.10"
Requires-Dist: scipy>=1.14.0; python_version >= "3.10"
Provides-Extra: dask
Requires-Dist: dask[dataframe]>=2.9.0; extra == "dask"
Requires-Dist: distributed>=2.11.0; extra == "dask"
Provides-Extra: docs
Requires-Dist: Sphinx>=6.1.3; extra == "docs"
Requires-Dist: sphinx-rtd-theme>=1.2.0; extra == "docs"
Requires-Dist: b2luigi; extra == "docs"
Requires-Dist: docutils>=0.18.1; extra == "docs"
Provides-Extra: matrixprofile
Requires-Dist: matrixprofile<2.0.0,>=1.1.10; extra == "matrixprofile"
Provides-Extra: testing
Requires-Dist: dask[dataframe]>=2.9.0; extra == "testing"
Requires-Dist: distributed>=2.11.0; extra == "testing"
Requires-Dist: pytest>=4.4.0; extra == "testing"
Requires-Dist: pytest-cov>=2.6.1; extra == "testing"
Requires-Dist: pytest-xdist>=1.26.1; extra == "testing"
Requires-Dist: pytest-benchmark>=3.0.0; extra == "testing"
Requires-Dist: mock>=2.0.0; extra == "testing"
Requires-Dist: matplotlib>=2.0.0; extra == "testing"
Requires-Dist: seaborn>=0.7.1; extra == "testing"
Requires-Dist: ipython>=5.3.0; extra == "testing"
Requires-Dist: notebook>=4.4.1; extra == "testing"
Requires-Dist: pandas-datareader>=0.5.0; extra == "testing"
Requires-Dist: pre-commit; extra == "testing"
